gwupload/__init__.py
gwupload/app.py
gwupload/cli.py
gwupload/py.typed
gwupload/service_cli.py
gwupload/stubs/__init__.py
gwupload/stubs/client/__init__.py
gwupload/stubs/client/client.py
gwupload/stubs/client/client_cli.py
gwupload/stubs/ingester/__init__.py
gwupload/stubs/ingester/ingester.py
gwupload/stubs/ingester/ingester_cli.py
gwupload/stubs/names.py
gwupload/stubs/stubs_cli.py
gridworks_uploader-1.0.2.dist-info/LICENSE
gridworks_uploader-1.0.2.dist-info/METADATA
gridworks_uploader-1.0.2.dist-info/WHEEL
gridworks_uploader-1.0.2.dist-info/entry_points.txt
gridworks_uploader-1.0.2.dist-info/RECORD
