Metadata-Version: 2.1
Name: gridworks-uploader
Version: 1.0.2
Summary: Gridworks Uploader
Home-page: https://github.com/SmoothStoneComputing/gridworks-uploader
License: MIT
Author: Andrew Schweitzer
Author-email: schweitz72@gmail.com
Requires-Python: >=3.11,<4.0
Classifier: Development Status :: 4 - Beta
Classifier: License :: OSI Approved :: MIT License
Classifier: Programming Language :: Python :: 3
Classifier: Programming Language :: Python :: 3.11
Classifier: Programming Language :: Python :: 3.12
Classifier: Programming Language :: Python :: 3.13
Requires-Dist: click (<8.2.0)
Requires-Dist: gridworks-proactor[tests] (>=4.1.0,<5.0.0)
Requires-Dist: gridworks-protocol (>=1.2.6,<2.0.0)
Requires-Dist: httpx (>=0.28.1,<0.29.0)
Requires-Dist: pydantic (>=2.11.2,<3.0.0)
Requires-Dist: pydantic-settings (>=2.8.1,<3.0.0)
Requires-Dist: typer (>=0.15.2,<0.16.0)
Project-URL: Changelog, https://github.com/SmoothStoneComputing/gridworks-uploader/releases
Project-URL: Documentation, https://gridworks-uploader.readthedocs.io
Project-URL: Repository, https://github.com/SmoothStoneComputing/gridworks-uploader
